reqwire/__init__.py
reqwire/__main__.py
reqwire/cli.py
reqwire/config.py
reqwire/errors.py
reqwire/scaffold.py
reqwire/helpers/__init__.py
reqwire/helpers/cli.py
reqwire/helpers/requirements.py
reqwire-0.2.1.dist-info/DESCRIPTION.rst
reqwire-0.2.1.dist-info/METADATA
reqwire-0.2.1.dist-info/RECORD
reqwire-0.2.1.dist-info/WHEEL
reqwire-0.2.1.dist-info/entry_points.txt
reqwire-0.2.1.dist-info/metadata.json
reqwire-0.2.1.dist-info/top_level.txt
