Metadata-Version: 2.0
Name: reqwire
Version: 0.2.1
Summary: reqwire: wire up Python requirements with pip-tools.
Home-page: https://github.com/darvid/reqwire
Author: David Gidwani
Author-email: david.gidwani@gmail.com
License: MIT
Platform: UNKNOWN
Classifier: Development Status :: 2 - Pre-Alpha
Classifier: Topic :: Software Development :: Libraries
Classifier: Topic :: Software Development :: Libraries :: Python Modules
Classifier: Topic :: Utilities
Classifier: Programming Language :: Python
Classifier: Programming Language :: Python :: 2
Classifier: Programming Language :: Python :: 2.7
Classifier: Programming Language :: Python :: 3
Classifier: Programming Language :: Python :: 3.3
Classifier: Programming Language :: Python :: 3.4
Classifier: Programming Language :: Python :: 3.5
Classifier: Programming Language :: Python :: 3.6
Classifier: Environment :: Console
Classifier: Intended Audience :: Developers
Classifier: License :: OSI Approved :: BSD License
Classifier: Operating System :: POSIX :: Linux
Classifier: Operating System :: Unix
Classifier: Operating System :: MacOS
Classifier: Operating System :: Microsoft :: Windows
Requires-Dist: atomicwrites
Requires-Dist: biome
Requires-Dist: emoji
Requires-Dist: fasteners
Requires-Dist: ordered-set
Requires-Dist: pip-tools
Requires-Dist: requests
Requires-Dist: sh
Requires-Dist: typing
Requires-Dist: enum34; python_version=="2.7"
Requires-Dist: pathlib2; python_version=="2.7"
